{
  "data": [
    {
      "symbol": "BTC/INR",
      "buy_price": 0,
      "status": "hold"
    },
    {
      "symbol": "ETH/INR",
      "buy_price": 0,
      "status": "auto"
    },
    {
      "symbol": "MATIC/INR",
      "buy_price": 0,
      "status": "hold"
    },
    {
      "symbol": "XRP/INR",
      "buy_price": 0,
      "status": "hold"
    },
    {
      "symbol": "ADA/INR",
      "buy_price": 0,
      "status": "hold"
    },
    {
      "symbol": "BAT/INR",
      "buy_price": 0,
      "status": "hold"
    },
    {
      "symbol": "BNB/INR",
      "buy_price": 0,
      "status": "auto"
    },
    {
      "symbol": "SOL/INR",
      "buy_price": 0,
      "status": "hold"
    },
    {
      "symbol": "NEAR/INR",
      "buy_price": 0,
      "status": "auto"
    },
    {
      "symbol": "SAND/INR",
      "buy_price": 0,
      "status": "hold"
    },
    {
      "symbol": "DOGE/INR",
      "buy_price": 0,
      "status": "hold"
    },
    {
      "symbol": "STX/INR",
      "buy_price": 0,
      "status": "hold"
    }
  ]
}